tkitRegex/__init__.py
tkitRegex/email.py
tkitRegex/re_scan.py
tkitRegex/regex_dict.py
tkitRegex/regex_plus.py
tkitRegex/spam.py
tkitRegex-0.0.0.116626169.dist-info/LICENSE
tkitRegex-0.0.0.116626169.dist-info/METADATA
tkitRegex-0.0.0.116626169.dist-info/WHEEL
tkitRegex-0.0.0.116626169.dist-info/top_level.txt
tkitRegex-0.0.0.116626169.dist-info/RECORD
