Metadata-Version: 2.1
Name: tkitRegex
Version: 0.0.0.116626169
Summary: Terry toolkit tkitRegex 正则合集 ,
Home-page: https://github.com/napoler/tkit-regex-tools
Author: Terry Chan
Author-email: napoler2008@gmail.com
License: UNKNOWN
Platform: UNKNOWN
License-File: LICENSE
Requires-Dist: pregex (>=2.1.0)
